{
  "schemaVersion": 5,
  "provider": "Ukrzaliznytsia public source fusion",
  "generatedAt": "2026-07-21T16:22:39.076Z",
  "sourceStatus": {
    "sourceId": "uz-public-fusion",
    "status": "online",
    "label": "UZ fusion: 67 событий · 3/5 источников доступны",
    "checkedAt": "2026-07-21T16:22:39.076Z",
    "capabilities": {
      "officialStatus": true,
      "forecast": true,
      "stationPassage": true,
      "gps": false,
      "scope": "public-passenger-and-commuter-events"
    }
  },
  "updates": [
    {
      "trainNumber": "119/120",
      "route": "Хелм → Дніпро-Головний",
      "origin": "Хелм",
      "destination": "Дніпро-Головний",
      "delayMinutes": 64,
      "delayLabel": "+1:04",
      "publicStatus": "В дорозі",
      "operationalStatus": "moving",
      "forecastDeparture": null,
      "forecastArrival": "06:38",
      "reliability": "Середня",
      "reason": "—",
      "updatedAt": "2026-07-21T16:21:07.323Z",
      "source": "https://uz-vezemo.uz.gov.ua/delayform/",
      "sourceId": "uz-delay-dashboard",
      "sourceEvidence": "official-public-dashboard",
      "positionEvidence": "none"
    },
    {
      "trainNumber": "63/64",
      "route": "Пшемисль Головний → Харків-Пас.",
      "origin": "Пшемисль Головний",
      "destination": "Харків-Пас.",
      "delayMinutes": 56,
      "delayLabel": "+0:56",
      "publicStatus": "В дорозі",
      "operationalStatus": "moving",
      "forecastDeparture": null,
      "forecastArrival": "06:58",
      "reliability": "Середня",
      "reason": "—",
      "updatedAt": "2026-07-21T16:21:07.323Z",
      "source": "https://uz-vezemo.uz.gov.ua/delayform/",
      "sourceId": "uz-delay-dashboard",
      "sourceEvidence": "official-public-dashboard",
      "positionEvidence": "none"
    },
    {
      "trainNumber": "103/104",
      "route": "Лозова-Пас. → Львів",
      "origin": "Лозова-Пас.",
      "destination": "Львів",
      "delayMinutes": 53,
      "delayLabel": "+0:53",
      "publicStatus": "В дорозі",
      "operationalStatus": "moving",
      "forecastDeparture": null,
      "forecastArrival": "09:29",
      "reliability": "Середня",
      "reason": "—",
      "updatedAt": "2026-07-21T16:21:07.323Z",
      "source": "https://uz-vezemo.uz.gov.ua/delayform/",
      "sourceId": "uz-delay-dashboard",
      "sourceEvidence": "official-public-dashboard",
      "positionEvidence": "none"
    },
    {
      "trainNumber": "9/10",
      "route": "Київ-Пас. → Будапешт-Келеті",
      "origin": "Київ-Пас.",
      "destination": "Будапешт-Келеті",
      "delayMinutes": 47,
      "delayLabel": "+0:47",
      "publicStatus": "В дорозі",
      "operationalStatus": "moving",
      "forecastDeparture": null,
      "forecastArrival": "06:47",
      "reliability": "Середня",
      "reason": "—",
      "updatedAt": "2026-07-21T16:21:07.323Z",
      "source": "https://uz-vezemo.uz.gov.ua/delayform/",
      "sourceId": "uz-delay-dashboard",
      "sourceEvidence": "official-public-dashboard",
      "positionEvidence": "none"
    },
    {
      "trainNumber": "749/750",
      "route": "Київ-Пас. → Ужгород",
      "origin": "Київ-Пас.",
      "destination": "Ужгород",
      "delayMinutes": 34,
      "delayLabel": "+0:34",
      "publicStatus": "В дорозі",
      "operationalStatus": "moving",
      "forecastDeparture": null,
      "forecastArrival": "01:10",
      "reliability": "Середня",
      "reason": "—",
      "updatedAt": "2026-07-21T16:21:07.323Z",
      "source": "https://uz-vezemo.uz.gov.ua/delayform/",
      "sourceId": "uz-delay-dashboard",
      "sourceEvidence": "official-public-dashboard",
      "positionEvidence": "none"
    },
    {
      "trainNumber": "749/750",
      "route": "Київ-Пас. → Відень Західний",
      "origin": "Київ-Пас.",
      "destination": "Відень Західний",
      "delayMinutes": 34,
      "delayLabel": "+0:34",
      "publicStatus": "В дорозі",
      "operationalStatus": "moving",
      "forecastDeparture": null,
      "forecastArrival": "09:57",
      "reliability": "Середня",
      "reason": "—",
      "updatedAt": "2026-07-21T16:21:07.323Z",
      "source": "https://uz-vezemo.uz.gov.ua/delayform/",
      "sourceId": "uz-delay-dashboard",
      "sourceEvidence": "official-public-dashboard",
      "positionEvidence": "none"
    },
    {
      "trainNumber": "13/14",
      "route": "Солотвино-1 → Київ-Пас.",
      "origin": "Солотвино-1",
      "destination": "Київ-Пас.",
      "delayMinutes": 24,
      "delayLabel": "+0:24",
      "publicStatus": "В дорозі",
      "operationalStatus": "moving",
      "forecastDeparture": null,
      "forecastArrival": "09:43",
      "reliability": "Середня",
      "reason": "—",
      "updatedAt": "2026-07-21T16:21:07.323Z",
      "source": "https://uz-vezemo.uz.gov.ua/delayform/",
      "sourceId": "uz-delay-dashboard",
      "sourceEvidence": "official-public-dashboard",
      "positionEvidence": "none"
    },
    {
      "trainNumber": "715/716",
      "route": "Київ-Пас. → Пшемисль Головний",
      "origin": "Київ-Пас.",
      "destination": "Пшемисль Головний",
      "delayMinutes": 21,
      "delayLabel": "+0:21",
      "publicStatus": "В дорозі",
      "operationalStatus": "moving",
      "forecastDeparture": null,
      "forecastArrival": "20:18",
      "reliability": "Середня",
      "reason": "—",
      "updatedAt": "2026-07-21T16:21:07.323Z",
      "source": "https://uz-vezemo.uz.gov.ua/delayform/",
      "sourceId": "uz-delay-dashboard",
      "sourceEvidence": "official-public-dashboard",
      "positionEvidence": "none"
    },
    {
      "trainNumber": "37/38",
      "route": "Ужгород → Одеса-Головна",
      "origin": "Ужгород",
      "destination": "Одеса-Головна",
      "delayMinutes": 23,
      "delayLabel": "+0:23",
      "publicStatus": "В дорозі",
      "operationalStatus": "moving",
      "forecastDeparture": null,
      "forecastArrival": "06:46",
      "reliability": "Середня",
      "reason": "—",
      "updatedAt": "2026-07-21T16:21:07.323Z",
      "source": "https://uz-vezemo.uz.gov.ua/delayform/",
      "sourceId": "uz-delay-dashboard",
      "sourceEvidence": "official-public-dashboard",
      "positionEvidence": "none"
    },
    {
      "trainNumber": "773/774",
      "route": "Конотоп-Пас. → Жмеринка-Пас.",
      "origin": "Конотоп-Пас.",
      "destination": "Жмеринка-Пас.",
      "delayMinutes": 20,
      "delayLabel": "+0:20",
      "publicStatus": "В дорозі",
      "operationalStatus": "moving",
      "forecastDeparture": null,
      "forecastArrival": "23:36",
      "reliability": "Середня",
      "reason": "—",
      "updatedAt": "2026-07-21T16:21:07.323Z",
      "source": "https://uz-vezemo.uz.gov.ua/delayform/",
      "sourceId": "uz-delay-dashboard",
      "sourceEvidence": "official-public-dashboard",
      "positionEvidence": "none"
    },
    {
      "trainNumber": "113/114",
      "route": "Харків-Пас. → Ужгород",
      "origin": "Харків-Пас.",
      "destination": "Ужгород",
      "delayMinutes": 17,
      "delayLabel": "+0:17",
      "publicStatus": "В дорозі",
      "operationalStatus": "moving",
      "forecastDeparture": null,
      "forecastArrival": "07:08",
      "reliability": "Середня",
      "reason": "—",
      "updatedAt": "2026-07-21T16:21:07.323Z",
      "source": "https://uz-vezemo.uz.gov.ua/delayform/",
      "sourceId": "uz-delay-dashboard",
      "sourceEvidence": "official-public-dashboard",
      "positionEvidence": "none"
    },
    {
      "trainNumber": "251/252",
      "route": "Київ-Пас. → Харків-Пас.",
      "origin": "Київ-Пас.",
      "destination": "Харків-Пас.",
      "delayMinutes": 17,
      "delayLabel": "+0:17",
      "publicStatus": "В дорозі",
      "operationalStatus": "moving",
      "forecastDeparture": null,
      "forecastArrival": "21:00",
      "reliability": "Середня",
      "reason": "—",
      "updatedAt": "2026-07-21T16:21:07.323Z",
      "source": "https://uz-vezemo.uz.gov.ua/delayform/",
      "sourceId": "uz-delay-dashboard",
      "sourceEvidence": "official-public-dashboard",
      "positionEvidence": "none"
    },
    {
      "trainNumber": "119/120",
      "route": "Дніпро-Головний → Хелм",
      "origin": "Дніпро-Головний",
      "destination": "Хелм",
      "delayMinutes": 16,
      "delayLabel": "+0:16",
      "publicStatus": "В дорозі",
      "operationalStatus": "moving",
      "forecastDeparture": null,
      "forecastArrival": "18:08",
      "reliability": "Середня",
      "reason": "—",
      "updatedAt": "2026-07-21T16:21:07.323Z",
      "source": "https://uz-vezemo.uz.gov.ua/delayform/",
      "sourceId": "uz-delay-dashboard",
      "sourceEvidence": "official-public-dashboard",
      "positionEvidence": "none"
    },
    {
      "trainNumber": "287/288",
      "route": "Київ-Пас. → Одеса-Головна",
      "origin": "Київ-Пас.",
      "destination": "Одеса-Головна",
      "delayMinutes": 14,
      "delayLabel": "+0:14",
      "publicStatus": "В дорозі",
      "operationalStatus": "moving",
      "forecastDeparture": null,
      "forecastArrival": "19:07",
      "reliability": "Середня",
      "reason": "—",
      "updatedAt": "2026-07-21T16:21:07.323Z",
      "source": "https://uz-vezemo.uz.gov.ua/delayform/",
      "sourceId": "uz-delay-dashboard",
      "sourceEvidence": "official-public-dashboard",
      "positionEvidence": "none"
    },
    {
      "trainNumber": "39/40",
      "route": "Запоріжжя-1 → Солотвино-1",
      "origin": "Запоріжжя-1",
      "destination": "Солотвино-1",
      "delayMinutes": 13,
      "delayLabel": "+0:13",
      "publicStatus": "В дорозі",
      "operationalStatus": "moving",
      "forecastDeparture": null,
      "forecastArrival": "17:43",
      "reliability": "Середня",
      "reason": "—",
      "updatedAt": "2026-07-21T16:21:07.323Z",
      "source": "https://uz-vezemo.uz.gov.ua/delayform/",
      "sourceId": "uz-delay-dashboard",
      "sourceEvidence": "official-public-dashboard",
      "positionEvidence": "none"
    },
    {
      "trainNumber": "101/102",
      "route": "Лозова-Пас. → Київ-Пас.",
      "origin": "Лозова-Пас.",
      "destination": "Київ-Пас.",
      "delayMinutes": 9,
      "delayLabel": "+0:09",
      "publicStatus": "В дорозі",
      "operationalStatus": "moving",
      "forecastDeparture": null,
      "forecastArrival": "19:26",
      "reliability": "Середня",
      "reason": "—",
      "updatedAt": "2026-07-21T16:21:07.323Z",
      "source": "https://uz-vezemo.uz.gov.ua/delayform/",
      "sourceId": "uz-delay-dashboard",
      "sourceEvidence": "official-public-dashboard",
      "positionEvidence": "none"
    },
    {
      "trainNumber": "39/40",
      "route": "Солотвино-1 → Запоріжжя-1",
      "origin": "Солотвино-1",
      "destination": "Запоріжжя-1",
      "delayMinutes": 5,
      "delayLabel": "+0:05",
      "publicStatus": "В дорозі",
      "operationalStatus": "moving",
      "forecastDeparture": null,
      "forecastArrival": "10:46",
      "reliability": "Середня",
      "reason": "—",
      "updatedAt": "2026-07-21T16:21:07.323Z",
      "source": "https://uz-vezemo.uz.gov.ua/delayform/",
      "sourceId": "uz-delay-dashboard",
      "sourceEvidence": "official-public-dashboard",
      "positionEvidence": "none"
    },
    {
      "trainNumber": "1/2",
      "route": "Харків-Пас. → Рахів",
      "origin": "Харків-Пас.",
      "destination": "Рахів",
      "delayMinutes": 164,
      "delayLabel": "+2:44",
      "publicStatus": "Готується",
      "operationalStatus": "station",
      "forecastDeparture": null,
      "forecastArrival": "17:50",
      "reliability": "Середня",
      "reason": "Вплив бойових дій",
      "updatedAt": "2026-07-21T16:21:07.322Z",
      "source": "https://uz-vezemo.uz.gov.ua/delayform/",
      "sourceId": "uz-delay-dashboard",
      "sourceEvidence": "official-public-dashboard",
      "positionEvidence": "none"
    },
    {
      "trainNumber": "123/124",
      "route": "Харків-Пас. → Чернівці",
      "origin": "Харків-Пас.",
      "destination": "Чернівці",
      "delayMinutes": 164,
      "delayLabel": "+2:44",
      "publicStatus": "Готується",
      "operationalStatus": "station",
      "forecastDeparture": null,
      "forecastArrival": "17:50",
      "reliability": "Середня",
      "reason": "Вплив бойових дій",
      "updatedAt": "2026-07-21T16:21:07.322Z",
      "source": "https://uz-vezemo.uz.gov.ua/delayform/",
      "sourceId": "uz-delay-dashboard",
      "sourceEvidence": "official-public-dashboard",
      "positionEvidence": "none"
    },
    {
      "trainNumber": "705/706",
      "route": "Пшемисль Головний → Київ-Пас.",
      "origin": "Пшемисль Головний",
      "destination": "Київ-Пас.",
      "delayMinutes": 126,
      "delayLabel": "+2:06",
      "publicStatus": "В дорозі",
      "operationalStatus": "moving",
      "forecastDeparture": null,
      "forecastArrival": "19:41",
      "reliability": "Середня",
      "reason": "Через затримку на кордоні",
      "updatedAt": "2026-07-21T16:21:07.322Z",
      "source": "https://uz-vezemo.uz.gov.ua/delayform/",
      "sourceId": "uz-delay-dashboard",
      "sourceEvidence": "official-public-dashboard",
      "positionEvidence": "none"
    },
    {
      "trainNumber": "17/18",
      "route": "Харків-Пас. → Ужгород",
      "origin": "Харків-Пас.",
      "destination": "Ужгород",
      "delayMinutes": 124,
      "delayLabel": "+2:04",
      "publicStatus": "В дорозі",
      "operationalStatus": "moving",
      "forecastDeparture": null,
      "forecastArrival": "11:34",
      "reliability": "Середня",
      "reason": "Вплив бойових дій",
      "updatedAt": "2026-07-21T16:21:07.322Z",
      "source": "https://uz-vezemo.uz.gov.ua/delayform/",
      "sourceId": "uz-delay-dashboard",
      "sourceEvidence": "official-public-dashboard",
      "positionEvidence": "none"
    },
    {
      "trainNumber": "775/776",
      "route": "Суми → Київ-Пас.",
      "origin": "Суми",
      "destination": "Київ-Пас.",
      "delayMinutes": 103,
      "delayLabel": "+1:43",
      "publicStatus": "В дорозі",
      "operationalStatus": "moving",
      "forecastDeparture": null,
      "forecastArrival": "20:48",
      "reliability": "Середня",
      "reason": "Вплив бойових дій",
      "updatedAt": "2026-07-21T16:21:07.322Z",
      "source": "https://uz-vezemo.uz.gov.ua/delayform/",
      "sourceId": "uz-delay-dashboard",
      "sourceEvidence": "official-public-dashboard",
      "positionEvidence": "none"
    },
    {
      "trainNumber": "749/750",
      "route": "Відень Західний → Київ-Пас.",
      "origin": "Відень Західний",
      "destination": "Київ-Пас.",
      "delayMinutes": 100,
      "delayLabel": "+1:40",
      "publicStatus": "В дорозі",
      "operationalStatus": "moving",
      "forecastDeparture": null,
      "forecastArrival": "19:24",
      "reliability": "Середня",
      "reason": "Через затримку на кордоні",
      "updatedAt": "2026-07-21T16:21:07.322Z",
      "source": "https://uz-vezemo.uz.gov.ua/delayform/",
      "sourceId": "uz-delay-dashboard",
      "sourceEvidence": "official-public-dashboard",
      "positionEvidence": "none"
    },
    {
      "trainNumber": "749/750",
      "route": "Ужгород → Київ-Пас.",
      "origin": "Ужгород",
      "destination": "Київ-Пас.",
      "delayMinutes": 100,
      "delayLabel": "+1:40",
      "publicStatus": "В дорозі",
      "operationalStatus": "moving",
      "forecastDeparture": null,
      "forecastArrival": "18:36",
      "reliability": "Середня",
      "reason": "Через затримку на кордоні",
      "updatedAt": "2026-07-21T16:21:07.322Z",
      "source": "https://uz-vezemo.uz.gov.ua/delayform/",
      "sourceId": "uz-delay-dashboard",
      "sourceEvidence": "official-public-dashboard",
      "positionEvidence": "none"
    },
    {
      "trainNumber": "63/64",
      "route": "Харків-Пас. → Пшемисль Головний",
      "origin": "Харків-Пас.",
      "destination": "Пшемисль Головний",
      "delayMinutes": 80,
      "delayLabel": "+1:20",
      "publicStatus": "В дорозі",
      "operationalStatus": "moving",
      "forecastDeparture": null,
      "forecastArrival": "18:19",
      "reliability": "Середня",
      "reason": "Вплив бойових дій",
      "updatedAt": "2026-07-21T16:21:07.322Z",
      "source": "https://uz-vezemo.uz.gov.ua/delayform/",
      "sourceId": "uz-delay-dashboard",
      "sourceEvidence": "official-public-dashboard",
      "positionEvidence": "none"
    },
    {
      "trainNumber": "79/80",
      "route": "Львів → Дніпро-Головний",
      "origin": "Львів",
      "destination": "Дніпро-Головний",
      "delayMinutes": 74,
      "delayLabel": "+1:14",
      "publicStatus": "В дорозі",
      "operationalStatus": "moving",
      "forecastDeparture": null,
      "forecastArrival": "07:29",
      "reliability": "Середня",
      "reason": "Через спізнення обігового поїзда",
      "updatedAt": "2026-07-21T16:21:07.322Z",
      "source": "https://uz-vezemo.uz.gov.ua/delayform/",
      "sourceId": "uz-delay-dashboard",
      "sourceEvidence": "official-public-dashboard",
      "positionEvidence": "none"
    },
    {
      "trainNumber": "289/290",
      "route": "Львів → Київ-Пас.",
      "origin": "Львів",
      "destination": "Київ-Пас.",
      "delayMinutes": 74,
      "delayLabel": "+1:14",
      "publicStatus": "В дорозі",
      "operationalStatus": "moving",
      "forecastDeparture": null,
      "forecastArrival": "23:39",
      "reliability": "Середня",
      "reason": "Через спізнення обігового поїзда",
      "updatedAt": "2026-07-21T16:21:07.322Z",
      "source": "https://uz-vezemo.uz.gov.ua/delayform/",
      "sourceId": "uz-delay-dashboard",
      "sourceEvidence": "official-public-dashboard",
      "positionEvidence": "none"
    },
    {
      "trainNumber": "9/10",
      "route": "Будапешт-Келеті → Київ-Пас.",
      "origin": "Будапешт-Келеті",
      "destination": "Київ-Пас.",
      "delayMinutes": 74,
      "delayLabel": "+1:14",
      "publicStatus": "В дорозі",
      "operationalStatus": "moving",
      "forecastDeparture": null,
      "forecastArrival": "20:30",
      "reliability": "Середня",
      "reason": "з технічних причин",
      "updatedAt": "2026-07-21T16:21:07.322Z",
      "source": "https://uz-vezemo.uz.gov.ua/delayform/",
      "sourceId": "uz-delay-dashboard",
      "sourceEvidence": "official-public-dashboard",
      "positionEvidence": "none"
    },
    {
      "trainNumber": "177/178",
      "route": "Львів → Київ-Пас.",
      "origin": "Львів",
      "destination": "Київ-Пас.",
      "delayMinutes": 74,
      "delayLabel": "+1:14",
      "publicStatus": "В дорозі",
      "operationalStatus": "moving",
      "forecastDeparture": null,
      "forecastArrival": "20:30",
      "reliability": "Середня",
      "reason": "з технічних причин",
      "updatedAt": "2026-07-21T16:21:07.322Z",
      "source": "https://uz-vezemo.uz.gov.ua/delayform/",
      "sourceId": "uz-delay-dashboard",
      "sourceEvidence": "official-public-dashboard",
      "positionEvidence": "none"
    },
    {
      "trainNumber": "6245",
      "origin": "Бахмач-Пасажирський",
      "destination": "Гребінка",
      "delayMinutes": null,
      "delayLabel": "",
      "publicStatus": "№6245 Бахмач-Пасажирський – Гребінка, притримаємо три стикові рейси:\n▶️",
      "operationalStatus": "station",
      "forecastDeparture": null,
      "forecastArrival": null,
      "reliability": "Официальный публичный канал",
      "reason": null,
      "updatedAt": "2026-07-21T16:03:03+00:00",
      "source": "https://t.me/s/UZprymisky",
      "sourceId": "uz-suburban-telegram",
      "sourceEvidence": "official-public-channel",
      "positionEvidence": "none",
      "reportedStation": null,
      "sourceEventUrl": "https://t.me/UZprymisky/4169"
    },
    {
      "trainNumber": "6823",
      "origin": "Гребінка",
      "destination": "Київ-Волинський",
      "delayMinutes": 30,
      "delayLabel": "+0:30",
      "publicStatus": "№6823 Гребінка – Київ-Волинський – до 30 хвилин\n▶️",
      "operationalStatus": "station",
      "forecastDeparture": null,
      "forecastArrival": null,
      "reliability": "Официальный публичный канал",
      "reason": null,
      "updatedAt": "2026-07-21T16:03:03+00:00",
      "source": "https://t.me/s/UZprymisky",
      "sourceId": "uz-suburban-telegram",
      "sourceEvidence": "official-public-channel",
      "positionEvidence": "none",
      "reportedStation": null,
      "sourceEventUrl": "https://t.me/UZprymisky/4169"
    },
    {
      "trainNumber": "6370",
      "origin": "Гребінка",
      "destination": "Ромодан",
      "delayMinutes": 20,
      "delayLabel": "+0:20",
      "publicStatus": "№6370 Гребінка – Ромодан – до 20 хвилин\n▶️",
      "operationalStatus": "station",
      "forecastDeparture": null,
      "forecastArrival": null,
      "reliability": "Официальный публичный канал",
      "reason": null,
      "updatedAt": "2026-07-21T16:03:03+00:00",
      "source": "https://t.me/s/UZprymisky",
      "sourceId": "uz-suburban-telegram",
      "sourceEvidence": "official-public-channel",
      "positionEvidence": "none",
      "reportedStation": null,
      "sourceEventUrl": "https://t.me/UZprymisky/4169"
    },
    {
      "trainNumber": "6095",
      "origin": "Гребінка",
      "destination": "Золотоноша-1",
      "delayMinutes": 20,
      "delayLabel": "+0:20",
      "publicStatus": "№6095 Гребінка — Золотоноша-1 – до 20 хвилин.\nРушимо з усіма на борту 🤝\n#Полтавщина #Київщина #Черкащина",
      "operationalStatus": "station",
      "forecastDeparture": null,
      "forecastArrival": null,
      "reliability": "Официальный публичный канал",
      "reason": null,
      "updatedAt": "2026-07-21T16:03:03+00:00",
      "source": "https://t.me/s/UZprymisky",
      "sourceId": "uz-suburban-telegram",
      "sourceEvidence": "official-public-channel",
      "positionEvidence": "none",
      "reportedStation": null,
      "sourceEventUrl": "https://t.me/UZprymisky/4169"
    },
    {
      "trainNumber": "853",
      "origin": "Харків",
      "destination": "Дніпро",
      "delayMinutes": 120,
      "delayLabel": "+2:00",
      "publicStatus": "№853 Харків – Дніпро відправився з початкової із затримкою 2 години.\n🔄 ⚡️ Затримались через запізнення попереднього рейсу, спричинене відсутністю напруги в контактній мережі на певних ділянках маршруту.\nВже в дорозі. Перепрошуємо за тривал",
      "operationalStatus": "moving",
      "forecastDeparture": null,
      "forecastArrival": null,
      "reliability": "Официальный публичный канал",
      "reason": null,
      "updatedAt": "2026-07-21T14:53:15+00:00",
      "source": "https://t.me/s/UZprymisky",
      "sourceId": "uz-suburban-telegram",
      "sourceEvidence": "official-public-channel",
      "positionEvidence": "none",
      "reportedStation": null,
      "sourceEventUrl": "https://t.me/UZprymisky/4168"
    },
    {
      "trainNumber": "6311",
      "origin": "Козятин-1",
      "destination": "Жмеринка зачекає на початковій пасажирів, які прямують",
      "delayMinutes": 25,
      "delayLabel": "+0:25",
      "publicStatus": "№6311 Козятин-1 – Жмеринка зачекає на початковій пасажирів, які прямують із Шепетівки.\n⏳️ Щоб пересадка відбулася, затримаємось орієнтовно на 25 хвилин.\nІ одразу в дорогу 🛤\n#Вінниччина",
      "operationalStatus": "station",
      "forecastDeparture": null,
      "forecastArrival": null,
      "reliability": "Официальный публичный канал",
      "reason": null,
      "updatedAt": "2026-07-21T14:25:30+00:00",
      "source": "https://t.me/s/UZprymisky",
      "sourceId": "uz-suburban-telegram",
      "sourceEvidence": "official-public-channel",
      "positionEvidence": "none",
      "reportedStation": null,
      "sourceEventUrl": "https://t.me/UZprymisky/4167"
    },
    {
      "trainNumber": "6548",
      "origin": "Конотоп-Пасажирський",
      "destination": "Шостка",
      "delayMinutes": 70,
      "delayLabel": "+1:10",
      "publicStatus": "№6548 Конотоп-Пасажирський – Шостка відправився з початкової із затримкою 1 година 10 хвилин.\n🚊 🕘 Поїзд",
      "operationalStatus": "moving",
      "forecastDeparture": null,
      "forecastArrival": null,
      "reliability": "Официальный публичный канал",
      "reason": null,
      "updatedAt": "2026-07-21T13:20:38+00:00",
      "source": "https://t.me/s/UZprymisky",
      "sourceId": "uz-suburban-telegram",
      "sourceEvidence": "official-public-channel",
      "positionEvidence": "none",
      "reportedStation": null,
      "sourceEventUrl": "https://t.me/UZprymisky/4165"
    },
    {
      "trainNumber": "6104",
      "origin": "Конотоп-Пасажирський",
      "destination": "Путивль",
      "delayMinutes": 67,
      "delayLabel": "+1:07",
      "publicStatus": "№6104 Конотоп-Пасажирський – Путивль прямує з початкової +1 година 7 хвилин.\nКурсуємо за маршрутами із додержанням безпекових протоколів 🛤\n#Сумщина",
      "operationalStatus": "moving",
      "forecastDeparture": null,
      "forecastArrival": null,
      "reliability": "Официальный публичный канал",
      "reason": null,
      "updatedAt": "2026-07-21T13:20:38+00:00",
      "source": "https://t.me/s/UZprymisky",
      "sourceId": "uz-suburban-telegram",
      "sourceEvidence": "official-public-channel",
      "positionEvidence": "none",
      "reportedStation": null,
      "sourceEventUrl": "https://t.me/UZprymisky/4165"
    },
    {
      "trainNumber": "6523",
      "origin": "",
      "destination": "",
      "delayMinutes": 50,
      "delayLabel": "+0:50",
      "publicStatus": "№6523 Ніжин – Гребінка, для збереження стиковки, орієнтовно до 50 хвилин притримаємо такі поїзди:\n🚊",
      "operationalStatus": "station",
      "forecastDeparture": null,
      "forecastArrival": null,
      "reliability": "Официальный публичный канал",
      "reason": null,
      "updatedAt": "2026-07-21T10:56:55+00:00",
      "source": "https://t.me/s/UZprymisky",
      "sourceId": "uz-suburban-telegram",
      "sourceEvidence": "official-public-channel",
      "positionEvidence": "none",
      "reportedStation": null,
      "sourceEventUrl": "https://t.me/UZprymisky/4164"
    },
    {
      "trainNumber": "6917",
      "origin": "Ніжин",
      "destination": "Київ-Пасажирський",
      "delayMinutes": 50,
      "delayLabel": "+0:50",
      "publicStatus": "№6917 Ніжин – Київ-Пасажирський прямує +50 хвилин до графіка. Затримались через пізнє прибуття попереднього рейсу.\nПерепрошуємо за очікування. Максимально мчимо до кінцевої та скорочуємо відставання 💨\n#Чернігівщина\n#Київщина",
      "operationalStatus": "moving",
      "forecastDeparture": null,
      "forecastArrival": null,
      "reliability": "Официальный публичный канал",
      "reason": null,
      "updatedAt": "2026-07-21T09:40:21+00:00",
      "source": "https://t.me/s/UZprymisky",
      "sourceId": "uz-suburban-telegram",
      "sourceEvidence": "official-public-channel",
      "positionEvidence": "none",
      "reportedStation": null,
      "sourceEventUrl": "https://t.me/UZprymisky/4163"
    },
    {
      "trainNumber": "854",
      "origin": "Дніпро-Головний",
      "destination": "Харків-Пасажирський",
      "delayMinutes": 70,
      "delayLabel": "+1:10",
      "publicStatus": "№854 Дніпро-Головний – Харків-Пасажирський прямує від станції Варварівка із затримкою 1 година 10 хвилин.\n🚊 Поїзд",
      "operationalStatus": "moving",
      "forecastDeparture": null,
      "forecastArrival": null,
      "reliability": "Официальный публичный канал",
      "reason": null,
      "updatedAt": "2026-07-21T08:26:19+00:00",
      "source": "https://t.me/s/UZprymisky",
      "sourceId": "uz-suburban-telegram",
      "sourceEvidence": "official-public-channel",
      "positionEvidence": "none",
      "reportedStation": null,
      "sourceEventUrl": "https://t.me/UZprymisky/4162"
    },
    {
      "trainNumber": "6516",
      "origin": "Златопіль",
      "destination": "Харків",
      "delayMinutes": null,
      "delayLabel": "",
      "publicStatus": "№6516 Златопіль – Харків відправився зі станції Златопіль на 1 годину понад графік з безпекових міркувань.\n⚡️ 🚊 Через відсутність напруги в контактній мережі, а також безпекову ситуацію затримується поїзд",
      "operationalStatus": "moving",
      "forecastDeparture": null,
      "forecastArrival": null,
      "reliability": "Официальный публичный канал",
      "reason": null,
      "updatedAt": "2026-07-21T08:26:19+00:00",
      "source": "https://t.me/s/UZprymisky",
      "sourceId": "uz-suburban-telegram",
      "sourceEvidence": "official-public-channel",
      "positionEvidence": "none",
      "reportedStation": null,
      "sourceEventUrl": "https://t.me/UZprymisky/4162"
    },
    {
      "trainNumber": "6454",
      "origin": "Ніжин",
      "destination": "Конотоп",
      "delayMinutes": 30,
      "delayLabel": "+0:30",
      "publicStatus": "№6454 Ніжин — Конотоп — до 30 хвилин.\nРушимо, як всі піднімуться на борт 🤝\n#Чернігівщина #Полтавщина #Сумщина",
      "operationalStatus": "moving",
      "forecastDeparture": null,
      "forecastArrival": null,
      "reliability": "Официальный публичный канал",
      "reason": null,
      "updatedAt": "2026-07-21T07:38:53+00:00",
      "source": "https://t.me/s/UZprymisky",
      "sourceId": "uz-suburban-telegram",
      "sourceEvidence": "official-public-channel",
      "positionEvidence": "none",
      "reportedStation": null,
      "sourceEventUrl": "https://t.me/UZprymisky/4161"
    },
    {
      "trainNumber": "6364",
      "origin": "Гребінка",
      "destination": "Ромодан",
      "delayMinutes": 15,
      "delayLabel": "+0:15",
      "publicStatus": "№6364 Гребінка – Ромодан відправиттсяиіз орієнтовною затримкою 15 хвилин.\n👫 Зачекаємо на початковій пасажирів поїзда",
      "operationalStatus": "station",
      "forecastDeparture": null,
      "forecastArrival": null,
      "reliability": "Официальный публичный канал",
      "reason": null,
      "updatedAt": "2026-07-21T05:28:27+00:00",
      "source": "https://t.me/s/UZprymisky",
      "sourceId": "uz-suburban-telegram",
      "sourceEvidence": "official-public-channel",
      "positionEvidence": "none",
      "reportedStation": null,
      "sourceEventUrl": "https://t.me/UZprymisky/4159"
    },
    {
      "trainNumber": "6802",
      "origin": "Київ-Волинський",
      "destination": "Гребінка для пересадки",
      "delayMinutes": null,
      "delayLabel": "",
      "publicStatus": "№6802 Київ-Волинський – Гребінка для пересадки.\nВсі будуть у вагонах – і вперед 💨\n#Полтавщина",
      "operationalStatus": "station",
      "forecastDeparture": null,
      "forecastArrival": null,
      "reliability": "Официальный публичный канал",
      "reason": null,
      "updatedAt": "2026-07-21T05:28:27+00:00",
      "source": "https://t.me/s/UZprymisky",
      "sourceId": "uz-suburban-telegram",
      "sourceEvidence": "official-public-channel",
      "positionEvidence": "none",
      "reportedStation": null,
      "sourceEventUrl": "https://t.me/UZprymisky/4159"
    },
    {
      "trainNumber": "6512",
      "origin": "Лозова",
      "destination": "Харків-Пасажирський",
      "delayMinutes": null,
      "delayLabel": "",
      "publicStatus": "№6512 Лозова – Харків-Пасажирський\n➡️",
      "operationalStatus": "moving",
      "forecastDeparture": null,
      "forecastArrival": null,
      "reliability": "Официальный публичный канал",
      "reason": null,
      "updatedAt": "2026-07-21T04:14:34+00:00",
      "source": "https://t.me/s/UZprymisky",
      "sourceId": "uz-suburban-telegram",
      "sourceEvidence": "official-public-channel",
      "positionEvidence": "none",
      "reportedStation": null,
      "sourceEventUrl": "https://t.me/UZprymisky/4158"
    },
    {
      "trainNumber": "6414",
      "origin": "Лозова",
      "destination": "Харків-Пасажирський",
      "delayMinutes": null,
      "delayLabel": "",
      "publicStatus": "№6414 Лозова – Харків-Пасажирський\n➡️",
      "operationalStatus": "moving",
      "forecastDeparture": null,
      "forecastArrival": null,
      "reliability": "Официальный публичный канал",
      "reason": null,
      "updatedAt": "2026-07-21T04:14:34+00:00",
      "source": "https://t.me/s/UZprymisky",
      "sourceId": "uz-suburban-telegram",
      "sourceEvidence": "official-public-channel",
      "positionEvidence": "none",
      "reportedStation": null,
      "sourceEventUrl": "https://t.me/UZprymisky/4158"
    },
    {
      "trainNumber": "6503",
      "origin": "Бірки",
      "destination": "Лозова",
      "delayMinutes": null,
      "delayLabel": "",
      "publicStatus": "№6503 Бірки – Лозова.\n🚊 На Чернігівщині поїзд",
      "operationalStatus": "moving",
      "forecastDeparture": null,
      "forecastArrival": null,
      "reliability": "Официальный публичный канал",
      "reason": null,
      "updatedAt": "2026-07-21T04:14:34+00:00",
      "source": "https://t.me/s/UZprymisky",
      "sourceId": "uz-suburban-telegram",
      "sourceEvidence": "official-public-channel",
      "positionEvidence": "none",
      "reportedStation": null,
      "sourceEventUrl": "https://t.me/UZprymisky/4158"
    },
    {
      "trainNumber": "6301",
      "origin": "Ніжин",
      "destination": "Чернігів плюсує 35 хвилин до графіка через шахедну небезпеку",
      "delayMinutes": 35,
      "delayLabel": "+0:35",
      "publicStatus": "№6301 Ніжин – Чернігів плюсує 35 хвилин до графіка через шахедну небезпеку.\nПросимо чітко виконувати вказівки залізничників під час можливих безпекових зупинок 🙏\n#Харківщина #Чернігівщина",
      "operationalStatus": "moving",
      "forecastDeparture": null,
      "forecastArrival": null,
      "reliability": "Официальный публичный канал",
      "reason": null,
      "updatedAt": "2026-07-21T04:14:34+00:00",
      "source": "https://t.me/s/UZprymisky",
      "sourceId": "uz-suburban-telegram",
      "sourceEvidence": "official-public-channel",
      "positionEvidence": "none",
      "reportedStation": null,
      "sourceEventUrl": "https://t.me/UZprymisky/4158"
    },
    {
      "trainNumber": "6277",
      "origin": "Лозова",
      "destination": "Дніпро-Головний",
      "delayMinutes": 45,
      "delayLabel": "+0:45",
      "publicStatus": "№6277 Лозова – Дніпро-Головний курсує із початкової +45 хвилин до графіка.\nЗатримались з безпекових міркувань.\n🛤 Вже в дорозі. Просимо подбати про свою безпеку та стежити за оголошеннями станціях 🙏\n#Харківщина #Дніпропетровщина",
      "operationalStatus": "moving",
      "forecastDeparture": null,
      "forecastArrival": null,
      "reliability": "Официальный публичный канал",
      "reason": null,
      "updatedAt": "2026-07-21T03:58:44+00:00",
      "source": "https://t.me/s/UZprymisky",
      "sourceId": "uz-suburban-telegram",
      "sourceEvidence": "official-public-channel",
      "positionEvidence": "none",
      "reportedStation": null,
      "sourceEventUrl": "https://t.me/UZprymisky/4157"
    },
    {
      "trainNumber": "6272",
      "origin": "Рудниця",
      "destination": "Гайворон",
      "delayMinutes": 50,
      "delayLabel": "+0:50",
      "publicStatus": "№6272 Рудниця – Гайворон затримується на початковій наразі на 1 годину 50 хвилин. Час затримки може змінитися.\nПросимо уважно слухати оголошення на місцях відправлення.\n🙏 Перепрошуємо за незручності.\n#Полтавщина #Черкащина #Вінниччина #Кір",
      "operationalStatus": "moving",
      "forecastDeparture": null,
      "forecastArrival": null,
      "reliability": "Официальный публичный канал",
      "reason": null,
      "updatedAt": "2026-07-21T02:49:01+00:00",
      "source": "https://t.me/s/UZprymisky",
      "sourceId": "uz-suburban-telegram",
      "sourceEvidence": "official-public-channel",
      "positionEvidence": "none",
      "reportedStation": null,
      "sourceEventUrl": "https://t.me/UZprymisky/4156"
    },
    {
      "trainNumber": "6091",
      "origin": "Гребінка",
      "destination": "Черкаси",
      "delayMinutes": 75,
      "delayLabel": "+1:15",
      "publicStatus": "№6091 Гребінка – Черкаси прямує із затримкою 1 година 15 хвилин.\n🚊 🕘 Поїзд",
      "operationalStatus": "moving",
      "forecastDeparture": null,
      "forecastArrival": null,
      "reliability": "Официальный публичный канал",
      "reason": null,
      "updatedAt": "2026-07-21T02:49:01+00:00",
      "source": "https://t.me/s/UZprymisky",
      "sourceId": "uz-suburban-telegram",
      "sourceEvidence": "official-public-channel",
      "positionEvidence": "none",
      "reportedStation": null,
      "sourceEventUrl": "https://t.me/UZprymisky/4156"
    },
    {
      "trainNumber": "892/891",
      "origin": "Славутич",
      "destination": "Київ-Волинський",
      "delayMinutes": 61,
      "delayLabel": "+1:01",
      "publicStatus": "№892/891 Славутич – Київ-Волинський прямує з початкової +01:01 через шахедну небезпеку в регіоні.\n#регіональний #Київщина",
      "operationalStatus": "moving",
      "forecastDeparture": null,
      "forecastArrival": null,
      "reliability": "Официальный публичный канал",
      "reason": null,
      "updatedAt": "2026-07-20T16:14:08+00:00",
      "source": "https://t.me/s/UZprymisky",
      "sourceId": "uz-suburban-telegram",
      "sourceEvidence": "official-public-channel",
      "positionEvidence": "none",
      "reportedStation": null,
      "sourceEventUrl": "https://t.me/UZprymisky/4155"
    },
    {
      "trainNumber": "6431",
      "origin": "Харків-Левада",
      "destination": "Савинці",
      "delayMinutes": null,
      "delayLabel": "",
      "publicStatus": "№6431 Харків-Левада – Савинці прямує з початкової з плюсом.\nПоїзд",
      "operationalStatus": "moving",
      "forecastDeparture": null,
      "forecastArrival": null,
      "reliability": "Официальный публичный канал",
      "reason": null,
      "updatedAt": "2026-07-20T15:21:39+00:00",
      "source": "https://t.me/s/UZprymisky",
      "sourceId": "uz-suburban-telegram",
      "sourceEvidence": "official-public-channel",
      "positionEvidence": "none",
      "reportedStation": null,
      "sourceEventUrl": "https://t.me/UZprymisky/4154"
    },
    {
      "trainNumber": "6525",
      "origin": "Харків",
      "destination": "Лозова",
      "delayMinutes": null,
      "delayLabel": "",
      "publicStatus": "№6525 Харків – Лозова зі станції Покотилівка.\nПоїзд",
      "operationalStatus": "moving",
      "forecastDeparture": null,
      "forecastArrival": null,
      "reliability": "Официальный публичный канал",
      "reason": null,
      "updatedAt": "2026-07-20T15:21:39+00:00",
      "source": "https://t.me/s/UZprymisky",
      "sourceId": "uz-suburban-telegram",
      "sourceEvidence": "official-public-channel",
      "positionEvidence": "reported-station-passage",
      "reportedStation": "Покотилівка",
      "sourceEventUrl": "https://t.me/UZprymisky/4154"
    },
    {
      "trainNumber": "6432",
      "origin": "Савинці",
      "destination": "Харків",
      "delayMinutes": null,
      "delayLabel": "",
      "publicStatus": "№6432 Савинці – Харків із зупинки Донець.",
      "operationalStatus": "moving",
      "forecastDeparture": null,
      "forecastArrival": null,
      "reliability": "Официальный публичный канал",
      "reason": null,
      "updatedAt": "2026-07-20T15:21:39+00:00",
      "source": "https://t.me/s/UZprymisky",
      "sourceId": "uz-suburban-telegram",
      "sourceEvidence": "official-public-channel",
      "positionEvidence": "reported-station-passage",
      "reportedStation": "Донець",
      "sourceEventUrl": "https://t.me/UZprymisky/4154"
    },
    {
      "trainNumber": "7001",
      "origin": "Харків",
      "destination": "Лозова",
      "delayMinutes": null,
      "delayLabel": "",
      "publicStatus": "№7001 Харків – Лозова із зупинки Широніне.",
      "operationalStatus": "moving",
      "forecastDeparture": null,
      "forecastArrival": null,
      "reliability": "Официальный публичный канал",
      "reason": null,
      "updatedAt": "2026-07-20T15:21:39+00:00",
      "source": "https://t.me/s/UZprymisky",
      "sourceId": "uz-suburban-telegram",
      "sourceEvidence": "official-public-channel",
      "positionEvidence": "reported-station-passage",
      "reportedStation": "Широніне",
      "sourceEventUrl": "https://t.me/UZprymisky/4154"
    },
    {
      "trainNumber": "6705",
      "origin": "Харків",
      "destination": "Зміїв ід зупинки Карачівка",
      "delayMinutes": null,
      "delayLabel": "",
      "publicStatus": "№6705 Харків – Зміїв ід зупинки Карачівка.",
      "operationalStatus": "moving",
      "forecastDeparture": null,
      "forecastArrival": null,
      "reliability": "Официальный публичный канал",
      "reason": null,
      "updatedAt": "2026-07-20T15:21:39+00:00",
      "source": "https://t.me/s/UZprymisky",
      "sourceId": "uz-suburban-telegram",
      "sourceEvidence": "official-public-channel",
      "positionEvidence": "none",
      "reportedStation": null,
      "sourceEventUrl": "https://t.me/UZprymisky/4154"
    },
    {
      "trainNumber": "6817",
      "origin": "Харків",
      "destination": "Чугуїв",
      "delayMinutes": null,
      "delayLabel": "",
      "publicStatus": "№6817 Харків – Чугуїв з початкової.",
      "operationalStatus": "moving",
      "forecastDeparture": null,
      "forecastArrival": null,
      "reliability": "Официальный публичный канал",
      "reason": null,
      "updatedAt": "2026-07-20T15:21:39+00:00",
      "source": "https://t.me/s/UZprymisky",
      "sourceId": "uz-suburban-telegram",
      "sourceEvidence": "official-public-channel",
      "positionEvidence": "none",
      "reportedStation": null,
      "sourceEventUrl": "https://t.me/UZprymisky/4154"
    },
    {
      "trainNumber": "6407",
      "origin": "Харків",
      "destination": "Ізюм",
      "delayMinutes": null,
      "delayLabel": "",
      "publicStatus": "№6407 Харків – Ізюм із зупинки Сезонна.\nДніпропетровщина ⤵️\nПрямуємо із затримками на маршрутах Дніпро – Пʼятихатки (+зворотно) та Дніпро – Лозова.\nПросимо слухати оголошення 📢\n#Харківщина #Дніпропетровщина",
      "operationalStatus": "moving",
      "forecastDeparture": null,
      "forecastArrival": null,
      "reliability": "Официальный публичный канал",
      "reason": null,
      "updatedAt": "2026-07-20T15:21:39+00:00",
      "source": "https://t.me/s/UZprymisky",
      "sourceId": "uz-suburban-telegram",
      "sourceEvidence": "official-public-channel",
      "positionEvidence": "reported-station-passage",
      "reportedStation": "Сезонна",
      "sourceEventUrl": "https://t.me/UZprymisky/4154"
    },
    {
      "trainNumber": "6093",
      "origin": "Гребінка",
      "destination": "Черкаси",
      "delayMinutes": 25,
      "delayLabel": "+0:25",
      "publicStatus": "№6093 Гребінка - Черкаси до 25 хвилин\nВсіх чекаємо на борту 🤝\n#Полтавщина #Черкащина",
      "operationalStatus": "moving",
      "forecastDeparture": null,
      "forecastArrival": null,
      "reliability": "Официальный публичный канал",
      "reason": null,
      "updatedAt": "2026-07-20T10:33:41+00:00",
      "source": "https://t.me/s/UZprymisky",
      "sourceId": "uz-suburban-telegram",
      "sourceEvidence": "official-public-channel",
      "positionEvidence": "none",
      "reportedStation": null,
      "sourceEventUrl": "https://t.me/UZprymisky/4153"
    },
    {
      "trainNumber": "6366",
      "origin": "Гребінка",
      "destination": "Ромодан",
      "delayMinutes": 40,
      "delayLabel": "+0:40",
      "publicStatus": "№6366 Гребінка – Ромодан до 40 хвилин\n🚊 ➡️",
      "operationalStatus": "moving",
      "forecastDeparture": null,
      "forecastArrival": null,
      "reliability": "Официальный публичный канал",
      "reason": null,
      "updatedAt": "2026-07-20T10:33:41+00:00",
      "source": "https://t.me/s/UZprymisky",
      "sourceId": "uz-suburban-telegram",
      "sourceEvidence": "official-public-channel",
      "positionEvidence": "none",
      "reportedStation": null,
      "sourceEventUrl": "https://t.me/UZprymisky/4153"
    },
    {
      "trainNumber": "6524/6523",
      "origin": "Ніжин",
      "destination": "Гребінка",
      "delayMinutes": null,
      "delayLabel": "",
      "publicStatus": "№6524/6523 Ніжин – Гребінка притримаємо низку приміських рейсів:\n🚊 ➡️",
      "operationalStatus": "moving",
      "forecastDeparture": null,
      "forecastArrival": null,
      "reliability": "Официальный публичный канал",
      "reason": null,
      "updatedAt": "2026-07-20T10:33:41+00:00",
      "source": "https://t.me/s/UZprymisky",
      "sourceId": "uz-suburban-telegram",
      "sourceEvidence": "official-public-channel",
      "positionEvidence": "none",
      "reportedStation": null,
      "sourceEventUrl": "https://t.me/UZprymisky/4153"
    },
    {
      "trainNumber": "6813",
      "origin": "Гребінка",
      "destination": "Київ",
      "delayMinutes": 25,
      "delayLabel": "+0:25",
      "publicStatus": "№6813 сполученням Гребінка - Київ до 25 хвилин\n🚊 ➡️",
      "operationalStatus": "moving",
      "forecastDeparture": null,
      "forecastArrival": null,
      "reliability": "Официальный публичный канал",
      "reason": null,
      "updatedAt": "2026-07-20T10:33:41+00:00",
      "source": "https://t.me/s/UZprymisky",
      "sourceId": "uz-suburban-telegram",
      "sourceEvidence": "official-public-channel",
      "positionEvidence": "none",
      "reportedStation": null,
      "sourceEventUrl": "https://t.me/UZprymisky/4153"
    },
    {
      "trainNumber": "6912",
      "origin": "Київ-Волинський",
      "destination": "Ніжин",
      "delayMinutes": null,
      "delayLabel": "",
      "publicStatus": "№6912 Київ-Волинський – Ніжин відправлення…",
      "operationalStatus": "moving",
      "forecastDeparture": null,
      "forecastArrival": null,
      "reliability": "Официальный публичный канал",
      "reason": null,
      "updatedAt": "2026-07-20T09:15:36+00:00",
      "source": "https://t.me/s/UZprymisky",
      "sourceId": "uz-suburban-telegram",
      "sourceEvidence": "official-public-channel",
      "positionEvidence": "none",
      "reportedStation": null,
      "sourceEventUrl": "https://t.me/UZprymisky/4152"
    },
    {
      "trainNumber": "6413",
      "origin": "Помічна",
      "destination": "Одеса",
      "delayMinutes": 75,
      "delayLabel": "+1:15",
      "publicStatus": "№6413 Помічна – Одеса з технічних причин прямує зі станції Людмилівка +01:15.\nВже в русі 💨\n#Миколаївщина #Одещина",
      "operationalStatus": "moving",
      "forecastDeparture": null,
      "forecastArrival": null,
      "reliability": "Официальный публичный канал",
      "reason": null,
      "updatedAt": "2026-07-20T05:20:17+00:00",
      "source": "https://t.me/s/UZprymisky",
      "sourceId": "uz-suburban-telegram",
      "sourceEvidence": "official-public-channel",
      "positionEvidence": "reported-station-passage",
      "reportedStation": "Людмилівка",
      "sourceEventUrl": "https://t.me/UZprymisky/4151"
    },
    {
      "trainNumber": "6902",
      "origin": "Київ-Волинський",
      "destination": "Ніжин",
      "delayMinutes": 27,
      "delayLabel": "+0:27",
      "publicStatus": "№6902 Київ-Волинський – Ніжин з Броварів плюсує +27 хвилин.\n❕ 🚊 Поїзд",
      "operationalStatus": "moving",
      "forecastDeparture": null,
      "forecastArrival": null,
      "reliability": "Официальный публичный канал",
      "reason": null,
      "updatedAt": "2026-07-20T03:42:52+00:00",
      "source": "https://t.me/s/UZprymisky",
      "sourceId": "uz-suburban-telegram",
      "sourceEvidence": "official-public-channel",
      "positionEvidence": "none",
      "reportedStation": null,
      "sourceEventUrl": "https://t.me/UZprymisky/4150"
    },
    {
      "trainNumber": "6905",
      "origin": "Ніжин",
      "destination": "Київ-Волинський",
      "delayMinutes": 24,
      "delayLabel": "+0:24",
      "publicStatus": "№6905 Ніжин – Київ-Волинський зі станції Бобрик відправився +24 хвилин.\nМаксимально намагаємось вирівняти графік, просимо уважно слухати оголошення дикторів 📢\n#Чернігівщина #Київщина",
      "operationalStatus": "moving",
      "forecastDeparture": null,
      "forecastArrival": null,
      "reliability": "Официальный публичный канал",
      "reason": null,
      "updatedAt": "2026-07-20T03:42:52+00:00",
      "source": "https://t.me/s/UZprymisky",
      "sourceId": "uz-suburban-telegram",
      "sourceEvidence": "official-public-channel",
      "positionEvidence": "reported-station-passage",
      "reportedStation": "Бобрик",
      "sourceEventUrl": "https://t.me/UZprymisky/4150"
    }
  ]
}
